CHANGES.rst
CONTRIBUTORS.rst
LICENSE.GPL
LICENSE.rst
MANIFEST.in
README.rst
README.txt
bootstrap.py
buildout.cfg
setup.cfg
setup.py
docs/INSTALL.txt
docs/index.rst
docs/tdf.templateuploadcenter.pdf
docs/html/genindex.html
docs/html/index.html
docs/html/search.html
docs/html/searchindex.js
docs/html/_images/create_template_center.png
docs/html/_images/create_template_linked_release.png
docs/html/_images/create_template_project.png
docs/html/_images/create_template_release.png
docs/html/_images/create_template_small_project.png
docs/html/_images/install_tdf_templateuploadcenter.png
docs/html/_images/navigation_add_templateuploadcenter.png
docs/html/_images/template_center_form01.png
docs/html/_images/template_center_sharing.png
docs/html/_images/template_linked_release_form01.png
docs/html/_images/template_linked_release_form02.png
docs/html/_images/template_linked_release_form03.png
docs/html/_images/template_linked_release_form04.png
docs/html/_images/template_project_form01.png
docs/html/_images/template_project_form02.png
docs/html/_images/template_project_form03.png
docs/html/_images/template_release_form01.png
docs/html/_images/template_release_form02.png
docs/html/_images/template_release_form03.png
docs/html/_images/template_release_form04.png
docs/html/_images/template_release_publish1.png
docs/html/_images/template_small_project_form01.png
docs/html/_images/template_small_project_form02.png
docs/html/_images/template_small_project_form03.png
docs/html/_images/template_small_project_form04.png
docs/html/_sources/index.rst.txt
docs/html/_sources/source/addnewtemplatecenter.rst.txt
docs/html/_sources/source/addnewtemplatelinkedrelease.rst.txt
docs/html/_sources/source/addnewtemplateproject.rst.txt
docs/html/_sources/source/addnewtemplateprojects.rst.txt
docs/html/_sources/source/addnewtemplaterelease.rst.txt
docs/html/_sources/source/addnewtemplatesmallproject.rst.txt
docs/html/_sources/source/installation.rst.txt
docs/html/_sources/source/messaging.rst.txt
tdf.templateuploadcenter.egg-info/PKG-INFO
tdf.templateuploadcenter.egg-info/SOURCES.txt
tdf.templateuploadcenter.egg-info/dependency_links.txt
tdf.templateuploadcenter.egg-info/entry_points.txt
tdf.templateuploadcenter.egg-info/namespace_packages.txt
tdf.templateuploadcenter.egg-info/not-zip-safe
tdf.templateuploadcenter.egg-info/requires.txt
tdf.templateuploadcenter.egg-info/top_level.txt
