Metadata-Version: 1.1
Name: tdf.templateuploadcenter
Version: 0.41
Summary: TDF Template Upload Center
Home-page: http://github.com/tdf/tdf.templateuploadcenter
Author: Andreas Mantke
Author-email: maand@gmx.de
License: GPL
Keywords: Plone Add-On LibreOffice template templateuploadcenter
Platform: UNKNOWN
Classifier: Framework :: Plone
Classifier: Programming Language :: Python
Classifier: Topic :: Software Development :: Libraries :: Python Modules
